strawberry/__init__.py
strawberry/apps.py
strawberry/fields/__init__.py
strawberry/fields/helpers.py
strawberry/fields/md5.py
strawberry/tests/__init__.py
strawberry/tests/base.py
strawberry/tests/test_fields.py
django_strawberry-0.1.2.dist-info/LICENSE_GPL2.0.txt
django_strawberry-0.1.2.dist-info/LICENSE_LGPL_2.1.txt
django_strawberry-0.1.2.dist-info/METADATA
django_strawberry-0.1.2.dist-info/WHEEL
django_strawberry-0.1.2.dist-info/top_level.txt
django_strawberry-0.1.2.dist-info/RECORD
